{
  "id": "clinical#screening_cues_5a3c89c2",
  "content": "to 1 month after trauma exposure.\nNote: Symptoms typically begin immediately after the trauma,\nbut persistence for at least 3 days and up to a month is needed\nto meet disorder criteria.\nD. The disturbance causes clinically significant distress or impairment\nin social, occupational, or other important areas of functioning.\nE. The disturbance is not attributable to the physiological effects of\na substance (e.g., medication or alcohol) or another medical\ncondition (e.g., mild traumatic brain injury) and is not better ex-\nplained by brief psychotic disorder.\nAdjustment Disorders\nA. The development of emotional or behavioral symptoms in re-\nsponse to an identifiable stressor(s) occurring within 3 months of\nthe onset of the stressor(s).\nB. These symptoms or behaviors are clinically significant, as evi-\ndenced by one or both of the following:\n1. Marked distress that is out of proportion to the severity or in-\ntensity of the stressor, taking into account the external con-\ntext and the cultural factors that might influence symptom\nseverity and presentation.\n152 Trauma- and Stressor-Related Disorders\n2. Significant impairment in social, occupational, or other im-\nportant areas of functioning.\nC. The stress-related disturbance does not meet the criteria for an-",
  "metadata": {
    "source": "DSM-5",
    "url": "https://psychiatry.org/",
    "condition": "General",
    "risk_band": "low",
    "topics": [
      "stress",
      "screening_cues",
      "management"
    ],
    "is_clinical": true,
    "is_advice": false
  },
  "index_text": "General — Screening Cues to 1 month after trauma exposure.\nNote: Symptoms typically begin immediately after the trauma,\nbut persistence for at least 3 days and up to a month is needed\nto meet disorder criteria.\nD. The disturbance causes clinically significant distress or impairment\nin social, occupational, or other important areas of functioning.\nE. The disturbance is not attributable to the physiological effects of\na substance (e.g., medication or alcohol) or another medical\ncondition (e.g., mild traumatic brain injury) and is not better ex-\nplained by brief psychotic disorder.\nAdjustment Disorders\nA. The development of emotional or behavioral symptoms in re-\nsponse to an identifiable stressor(s) occurring within 3 months of\nthe onset of the stressor(s).\nB. These symptoms or behaviors are clinically significant, as evi-\ndenced by one or both of the following:\n1. Marked distress that is out of proportion to the severity or in-\ntensity of the stressor, taking into account the external con-\ntext and the cultural factors that might influence symptom\nseverity and presentation.\n152 Trauma- and Stressor-Related Disorders\n2. Significant impairment in social, occupational, or other im-\nportant areas of functioning.\nC. The stress-related disturbance does not meet the criteria for an- To 1 month after trauma exposure. note: symptoms typically begin immediately after the trauma,\nbut persistence for at least 3 days and up to a month is needed\nto meet disorder criteria."
}