{
  "id": "clinical#screening_cues_33ef6d3b",
  "content": "use disorder is comorbid with the substance-induced obsessive-\ncompulsive and related disorder, the 4th position character is “1,” and\nthe clinician should record “mild [substance] use disorder” before the\nsubstance-induced obsessive-compulsive and related disorder (e.g.,\n“mild cocaine use disorder with cocaine-induced obsessive-compul-\nsive and related disorder”). If a moderate or severe substance use\ndisorder is comorbid with the substance-induced obsessive-compul-\nsive and related disorder, the 4th position character is “2,” and the cli-\nnician should record “moderate [substance] use disorder” or “severe\n[substance] use disorder,” depending on the severity of the comorbid\nsubstance use disorder. If there is no comorbid substance use disor-\nder (e.g., after a one-time heavy use of the substance), then the 4th\nposition character is “9,” and the clinician should record only the sub-\nstance-induced obsessive-compulsive and related disorder.\nICD-10-CM\nWith use\nWith use disorder,\nICD-9- disorder, moderate Without use\nCM mild or severe disorder\nAmphetamine 292.89 F15.188 F15.288 F15.988\n(or other stimulant)\nCocaine 292.89 F14.188 F14.288 F14.988\nOther (or unknown) 292.89 F19.188 F19.288 F19.988\nsubstance\nSpecify if (see Table 1 in the chapter “Substance-Related and Addic-\ntive Disorders” for diagnoses associated with substance class):\nWith onset during intoxication: If the criteria are met for intox-",
  "metadata": {
    "source": "DSM-5",
    "url": "https://psychiatry.org/",
    "condition": "General",
    "risk_band": "low",
    "topics": [
      "screening_cues"
    ],
    "is_clinical": true,
    "is_advice": false
  },
  "index_text": "General — Screening Cues use disorder is comorbid with the substance-induced obsessive-\ncompulsive and related disorder, the 4th position character is “1,” and\nthe clinician should record “mild [substance] use disorder” before the\nsubstance-induced obsessive-compulsive and related disorder (e.g.,\n“mild cocaine use disorder with cocaine-induced obsessive-compul-\nsive and related disorder”). If a moderate or severe substance use\ndisorder is comorbid with the substance-induced obsessive-compul-\nsive and related disorder, the 4th position character is “2,” and the cli-\nnician should record “moderate [substance] use disorder” or “severe\n[substance] use disorder,” depending on the severity of the comorbid\nsubstance use disorder. If there is no comorbid substance use disor-\nder (e.g., after a one-time heavy use of the substance), then the 4th\nposition character is “9,” and the clinician should record only the sub-\nstance-induced obsessive-compulsive and related disorder.\nICD-10-CM\nWith use\nWith use disorder,\nICD-9- disorder, moderate Without use\nCM mild or severe disorder\nAmphetamine 292.89 F15.188 F15.288 F15.988\n(or other stimulant)\nCocaine 292.89 F14.188 F14.288 F14.988\nOther (or unknown) 292.89 F19.188 F19.288 F19.988\nsubstance\nSpecify if (see Table 1 in the chapter “Substance-Related and Addic-\ntive Disorders” for diagnoses associated with substance class):\nWith onset during intoxication: If the criteria are met for intox- Use disorder is comorbid with the substance-induced obsessive-\ncompulsive and related disorder, the 4th position character is “1,” and\nthe clinician should record “mild [substance] use disorder” before the\nsubstance-indu..."
}