{
  "id": "clinical#risk_safety_217bb93e",
  "content": "of that required for the diagnosis, or in which some, but not all, di-\nagnostic criteria for delirium are met.\nUnspecified Delirium\n780.09 (R41.0)\nThis category applies to presentations in which symptoms character-\nistic of delirium that cause clinically significant distress or impairment\nin social, occupational, or other important areas of functioning predom-\ninate but do not meet the full criteria for delirium or any of the disorders\nin the neurocognitive disorders diagnostic class. The unspecified delir-\nium category is used in situations in which the clinician chooses not to\nspecify the reason that the criteria are not met for delirium, and in-\ncludes presentations for which there is insufficient information to make\na more specific diagnosis (e.g., in emergency room settings).\nMajor Neurocognitive Disorder 299\nMajor and Mild Neurocognitive\nDisorders\nMajor Neurocognitive Disorder\nA. Evidence of significant cognitive decline from a previous level of\nperformance in one or more cognitive domains (complex atten-\ntion, executive function, learning and memory, language, per-\nceptual-motor, or social cognition) based on:\n1. Concern of the individual, a knowledgeable informant, or the\nclinician that there has been a significant decline in cognitive\nfunction; and\n2. A substantial impairment in cognitive performance, prefera-",
  "metadata": {
    "source": "DSM-5",
    "url": "https://psychiatry.org/",
    "condition": "General",
    "risk_band": "medium",
    "topics": [
      "stress",
      "risk_safety",
      "screening_cues",
      "referral",
      "management"
    ],
    "is_clinical": true,
    "is_advice": false
  },
  "index_text": "General — Risk Safety of that required for the diagnosis, or in which some, but not all, di-\nagnostic criteria for delirium are met.\nUnspecified Delirium\n780.09 (R41.0)\nThis category applies to presentations in which symptoms character-\nistic of delirium that cause clinically significant distress or impairment\nin social, occupational, or other important areas of functioning predom-\ninate but do not meet the full criteria for delirium or any of the disorders\nin the neurocognitive disorders diagnostic class. The unspecified delir-\nium category is used in situations in which the clinician chooses not to\nspecify the reason that the criteria are not met for delirium, and in-\ncludes presentations for which there is insufficient information to make\na more specific diagnosis (e.g., in emergency room settings).\nMajor Neurocognitive Disorder 299\nMajor and Mild Neurocognitive\nDisorders\nMajor Neurocognitive Disorder\nA. Evidence of significant cognitive decline from a previous level of\nperformance in one or more cognitive domains (complex atten-\ntion, executive function, learning and memory, language, per-\nceptual-motor, or social cognition) based on:\n1. Concern of the individual, a knowledgeable informant, or the\nclinician that there has been a significant decline in cognitive\nfunction; and\n2. A substantial impairment in cognitive performance, prefera- Of that required for the diagnosis, or in which some, but not all, di-\nagnostic criteria for delirium are met. unspecified delirium\n780.09 (r41.0)\nthis category applies to presentations in which symptoms character-\nistic..."
}