{
  "id": "clinical#screening_cues_efc26647",
  "content": "among children and adolescents with cyclothymic disorder – particularly attention deficit\nhyperactivity disorder.\nMood disorders | Cyclothymic disorder\n242 Clinical Descriptions and Diagnostic Requirements for ICD-11 Mental, Behavioural or Neurodevelopmental Disorders\nCulture-related features\n• Little information is available about cultural influences on cyclothymic disorder. The\ninformation on culture-related features for bipolar type I and bipolar type II disorders\n(p. 237) may be relevant.\nBoundaries with other disorders and conditions (differential diagnosis)\nBoundary with single episode depressive disorder and recurrent depressive disorder\nDuring the first 2 years of the disorder, depressive periods in cyclothymic disorder should not\nbe sufficient to meet the diagnostic requirements for a depressive episode. Outside this 2-year\nperiod, there may be instances in which the symptoms are severe enough to constitute a depressive\nepisode. In such cases, if there is no history of hypomanic episodes, single episode depressive\ndisorder or recurrent depressive disorder may be diagnosed along with cyclothymic disorder.\nBoundary with bipolar type I disorder\nIf the number and severity of symptoms reaches the diagnostic threshold for a manic episode\nor a mixed episode in the context of an ongoing cyclothymic disorder, the diagnosis should be\nchanged to bipolar type I disorder.",
  "metadata": {
    "source": "WHO ICD-11",
    "url": "https://icd.who.int/",
    "condition": "General",
    "risk_band": "low",
    "topics": [
      "communication_tips",
      "screening_cues"
    ],
    "is_clinical": true,
    "is_advice": false
  },
  "index_text": "General — Screening Cues among children and adolescents with cyclothymic disorder – particularly attention deficit\nhyperactivity disorder.\nMood disorders | Cyclothymic disorder\n242 Clinical Descriptions and Diagnostic Requirements for ICD-11 Mental, Behavioural or Neurodevelopmental Disorders\nCulture-related features\n• Little information is available about cultural influences on cyclothymic disorder. The\ninformation on culture-related features for bipolar type I and bipolar type II disorders\n(p. 237) may be relevant.\nBoundaries with other disorders and conditions (differential diagnosis)\nBoundary with single episode depressive disorder and recurrent depressive disorder\nDuring the first 2 years of the disorder, depressive periods in cyclothymic disorder should not\nbe sufficient to meet the diagnostic requirements for a depressive episode. Outside this 2-year\nperiod, there may be instances in which the symptoms are severe enough to constitute a depressive\nepisode. In such cases, if there is no history of hypomanic episodes, single episode depressive\ndisorder or recurrent depressive disorder may be diagnosed along with cyclothymic disorder.\nBoundary with bipolar type I disorder\nIf the number and severity of symptoms reaches the diagnostic threshold for a manic episode\nor a mixed episode in the context of an ongoing cyclothymic disorder, the diagnosis should be\nchanged to bipolar type I disorder. Among children and adolescents with cyclothymic disorder – particularly attention deficit\nhyperactivity disorder. mood disorders | cyclothymic disorder\n242 clinical descriptions and diagnostic requirements for icd-11 men..."
}