{
  "id": "clinical#screening_cues_5531cb4a",
  "content": "context of separation from key attachment figures, an additional diagnosis of panic disorder is\nnot warranted, and the presence of panic attacks may be indicated using the with panic attacks\nspecifier. However, if unexpected panic attacks also occur, an additional diagnosis of panic\ndisorder may be assigned.\nBoundary with agoraphobia\nIn agoraphobia, individuals avoid a variety of situations, including leaving home alone, but the\nfear or anxiety is centred on the possibility that help will not be available in the event of a panic\nattack or other incapacitating or embarrassing symptoms rather than concerns about separation\nfrom key attachment figures.\nBoundary with social anxiety disorder\nIn social anxiety disorder, the avoidance of social situations is in response to fear or anxiety\nabout being negatively evaluated by others rather than concerns about being separated from key\nattachment figures.\nBoundary with depressive disorders\nBeliefs of social inadequacy, rejection and failure are common in depressive disorders, and\nmay be associated with avoidance of leaving the home and being separated from loved ones.\nHowever, unlike in separation anxiety disorder, these symptoms occur almost exclusively during\na depressive episode.\nBoundary with post-traumatic stress disorder",
  "metadata": {
    "source": "WHO ICD-11",
    "url": "https://icd.who.int/",
    "condition": "General",
    "risk_band": "low",
    "topics": [
      "stress",
      "communication_tips",
      "screening_cues"
    ],
    "is_clinical": true,
    "is_advice": false
  },
  "index_text": "General — Screening Cues context of separation from key attachment figures, an additional diagnosis of panic disorder is\nnot warranted, and the presence of panic attacks may be indicated using the with panic attacks\nspecifier. However, if unexpected panic attacks also occur, an additional diagnosis of panic\ndisorder may be assigned.\nBoundary with agoraphobia\nIn agoraphobia, individuals avoid a variety of situations, including leaving home alone, but the\nfear or anxiety is centred on the possibility that help will not be available in the event of a panic\nattack or other incapacitating or embarrassing symptoms rather than concerns about separation\nfrom key attachment figures.\nBoundary with social anxiety disorder\nIn social anxiety disorder, the avoidance of social situations is in response to fear or anxiety\nabout being negatively evaluated by others rather than concerns about being separated from key\nattachment figures.\nBoundary with depressive disorders\nBeliefs of social inadequacy, rejection and failure are common in depressive disorders, and\nmay be associated with avoidance of leaving the home and being separated from loved ones.\nHowever, unlike in separation anxiety disorder, these symptoms occur almost exclusively during\na depressive episode.\nBoundary with post-traumatic stress disorder Context of separation from key attachment figures, an additional diagnosis of panic disorder is\nnot warranted, and the presence of panic attacks may be indicated using the with panic attacks\nspecifier. however, if unexpe..."
}