{
  "id": "clinical#screening_cues_d7be2586",
  "content": "provided by the relevant health system or government.\nIn a couple of specific instances (e.g. ICD-11 Body dysmorphic disorder), coding information\nprovided in The ICD-10 classification of mental and behavioural disorders: clinical descriptions and\ndiagnostic guidelines is not consistent with current evidence. The mappings provided in the table\nare consistent with the ICD-11 conceptualizations in these cases, with such deviations described\nin the “Notes” column.\n754 Clinical Descriptions and Diagnostic Requirements for ICD-11 Mental, Behavioural or Neurodevelopmental Disorders\nICD-11 ICD-10 Notes\nNeurodevelopmental disorders\n6A00 Disorders of intellectual development\n6A00.0 Disorder of intellectual development, mild F70 Mild mental retardation\n4-character code: F70.9 Mild mental retardation without\nmention of impairment of behaviour\n6A00.1 Disorder of intellectual development, moderate F71 Moderate mental retardation\n4-character code: F71.9 Moderate mental retardation without\nmention of impairment of behaviour\n6A00.2 Disorder of intellectual development, severe F72 Severe mental retardation\n4-character code: F72.9 Severe mental retardation without\nmention of impairment of behaviour\n6A00.3 Disorder of intellectual development, profound F73 Profound mental retardation\n4-character code: F73.9 Profound mental retardation without\nmention of impairment of behaviour\n6A00.4 Disorder of intellectual development, F78 Other mental retardation\nprovisional\n4-character code: F78.9 Other mental retardation without\nmention of impairment of behaviour",
  "metadata": {
    "source": "WHO ICD-11",
    "url": "https://icd.who.int/",
    "condition": "General",
    "risk_band": "low",
    "topics": [
      "screening_cues"
    ],
    "is_clinical": true,
    "is_advice": false
  },
  "index_text": "General — Screening Cues provided by the relevant health system or government.\nIn a couple of specific instances (e.g. ICD-11 Body dysmorphic disorder), coding information\nprovided in The ICD-10 classification of mental and behavioural disorders: clinical descriptions and\ndiagnostic guidelines is not consistent with current evidence. The mappings provided in the table\nare consistent with the ICD-11 conceptualizations in these cases, with such deviations described\nin the “Notes” column.\n754 Clinical Descriptions and Diagnostic Requirements for ICD-11 Mental, Behavioural or Neurodevelopmental Disorders\nICD-11 ICD-10 Notes\nNeurodevelopmental disorders\n6A00 Disorders of intellectual development\n6A00.0 Disorder of intellectual development, mild F70 Mild mental retardation\n4-character code: F70.9 Mild mental retardation without\nmention of impairment of behaviour\n6A00.1 Disorder of intellectual development, moderate F71 Moderate mental retardation\n4-character code: F71.9 Moderate mental retardation without\nmention of impairment of behaviour\n6A00.2 Disorder of intellectual development, severe F72 Severe mental retardation\n4-character code: F72.9 Severe mental retardation without\nmention of impairment of behaviour\n6A00.3 Disorder of intellectual development, profound F73 Profound mental retardation\n4-character code: F73.9 Profound mental retardation without\nmention of impairment of behaviour\n6A00.4 Disorder of intellectual development, F78 Other mental retardation\nprovisional\n4-character code: F78.9 Other mental retardation without\nmention of impairment of behaviour Provided by the relevant health system or government. in a couple of specific instances (e.g."
}