{
  "id": "clinical#screening_cues_e31655fd",
  "content": "paralyses or sensory loss – in sociocultural settings where such symptoms are common.\n• In some societies, presentations of partial dissociative identity disorder may occur after\nstressful exposures (e.g. recurrent parental affect dysregulation), which may or may not\ninvolve physical or sexual abuse. The tendency towards dissociative responses to stressors\nmay be increased in cultures with less individualistic (“bounded”) conceptions of the self,\nor in circumstances of socioeconomic deprivation.\nSex- and/or gender-related features\n• Females appear to be more likely to experience identity intrusions.\nDissociative disorders | Partial dissociative identity disorder\n390 Clinical Descriptions and Diagnostic Requirements for ICD-11 Mental, Behavioural or Neurodevelopmental Disorders\nBoundaries with other disorders and conditions (differential diagnosis)\nBoundary with trance disorder and possession trance disorder\nSome dissociative intrusions in partial dissociative identity disorder may resemble trance states,\nbut trance disorder is not characterized by the presence of two or more distinct personality states.\nIn possession trance disorder, the individual’s normal sense of personal identity is replaced by an\nexternal “possessing” identity, which is attributed to the influence of a spirit, power, deity or other\nspiritual entity. Behaviours or movements are experienced as being controlled by the possessing",
  "metadata": {
    "source": "WHO ICD-11",
    "url": "https://icd.who.int/",
    "condition": "General",
    "risk_band": "low",
    "topics": [
      "stress",
      "emotions",
      "communication_tips",
      "screening_cues"
    ],
    "is_clinical": true,
    "is_advice": false
  },
  "index_text": "General — Screening Cues paralyses or sensory loss – in sociocultural settings where such symptoms are common.\n• In some societies, presentations of partial dissociative identity disorder may occur after\nstressful exposures (e.g. recurrent parental affect dysregulation), which may or may not\ninvolve physical or sexual abuse. The tendency towards dissociative responses to stressors\nmay be increased in cultures with less individualistic (“bounded”) conceptions of the self,\nor in circumstances of socioeconomic deprivation.\nSex- and/or gender-related features\n• Females appear to be more likely to experience identity intrusions.\nDissociative disorders | Partial dissociative identity disorder\n390 Clinical Descriptions and Diagnostic Requirements for ICD-11 Mental, Behavioural or Neurodevelopmental Disorders\nBoundaries with other disorders and conditions (differential diagnosis)\nBoundary with trance disorder and possession trance disorder\nSome dissociative intrusions in partial dissociative identity disorder may resemble trance states,\nbut trance disorder is not characterized by the presence of two or more distinct personality states.\nIn possession trance disorder, the individual’s normal sense of personal identity is replaced by an\nexternal “possessing” identity, which is attributed to the influence of a spirit, power, deity or other\nspiritual entity. Behaviours or movements are experienced as being controlled by the possessing Paralyses or sensory loss – in sociocultural settings where such symptoms are common. • in some societies, presentations of partial dissociative identity disorder may occur after\nstressful exposures (e.g."
}