{
  "id": "clinical#risk_safety_ed69f10c",
  "content": "Additional clinical features\n• Intimate partner sexual abuse is associated with an increased risk of physical injury and\nneed for medical attention.\n• Intimate partner sexual abuse is associated with an increased risk of poor physical health\nand of development of a chronic disease.\n• Intimate partner sexual abuse is associated with increased risk of various mental disorders\n(e.g. depressive disorders, anxiety and fear-related disorders, disorders due to substance\nuse), as well as suicidality.\nBoundary with normality (threshold)\n• Sexual violation and coercion are not part of healthy functioning relationships.\nRelationship problems and maltreatment | Relationship distress and current or past maltreatment by spouse or partner Relationship problems and maltreatment | Relationship distress and current or past maltreatment by spouse or partner\nRelationship problems and maltreatment 717\nDevelopmental presentations\n• In general, adolescents and young adults are at greater risk of being victims of intimate\npartner sexual abuse because the rate of sexually abusive acts among perpetrators tends to\ndecrease across the lifespan.\nBoundaries with other disorders and conditions (differential diagnosis)\nBoundary with relationship distress with spouse or partner\nIntimate partner sexual abuse may be, but is not always, associated with relationship distress with",
  "metadata": {
    "source": "WHO ICD-11",
    "url": "https://icd.who.int/",
    "condition": "General",
    "risk_band": "high",
    "topics": [
      "stress",
      "relationships",
      "communication_tips",
      "risk_safety",
      "screening_cues",
      "management"
    ],
    "is_clinical": true,
    "is_advice": false
  },
  "index_text": "General — Risk Safety Additional clinical features\n• Intimate partner sexual abuse is associated with an increased risk of physical injury and\nneed for medical attention.\n• Intimate partner sexual abuse is associated with an increased risk of poor physical health\nand of development of a chronic disease.\n• Intimate partner sexual abuse is associated with increased risk of various mental disorders\n(e.g. depressive disorders, anxiety and fear-related disorders, disorders due to substance\nuse), as well as suicidality.\nBoundary with normality (threshold)\n• Sexual violation and coercion are not part of healthy functioning relationships.\nRelationship problems and maltreatment | Relationship distress and current or past maltreatment by spouse or partner Relationship problems and maltreatment | Relationship distress and current or past maltreatment by spouse or partner\nRelationship problems and maltreatment 717\nDevelopmental presentations\n• In general, adolescents and young adults are at greater risk of being victims of intimate\npartner sexual abuse because the rate of sexually abusive acts among perpetrators tends to\ndecrease across the lifespan.\nBoundaries with other disorders and conditions (differential diagnosis)\nBoundary with relationship distress with spouse or partner\nIntimate partner sexual abuse may be, but is not always, associated with relationship distress with Additional clinical features\n• intimate partner sexual abuse is associated with an increased nguy cơ of physical injury and\nneed for medical attention. • intimate partner sexual abuse is associated with an increased nguy..."
}