{
  "id": "clinical#screening_cues_0ee98522",
  "content": "6C4E.700 … with depressive symptoms\n6C4E.701 … with manic symptoms\n6C4E.702 … with mixed depressive and manic symptoms\n6C4E.70Z … unspecified\n6C4F.70 Mood disorder induced by multiple specified psychoactive\nsubstances\nSpecify clinical presentation:\n6C4F.700 … with depressive symptoms\n6C4F.701 … with manic symptoms\n6C4F.702 … with mixed depressive and manic symptoms\n6C4F.70Z … unspecified\n6C4G.70 Mood disorder induced by unknown or unspecified psychoactive\nsubstances\nSpecify clinical presentation:\n6C4G.700 … with depressive symptoms\n6C4G.701 … with manic symptoms\nList of categories 51\n6C4G.702 … with mixed depressive and manic symptoms\n6C4G.70Z … unspecified\nFrom secondary mental or behavioural syndromes associated with\ndisorders and diseases classified elsewhere:\n6E62 Secondary mood syndrome\nSpecify clinical presentation:\n6E62.0 … with depressive symptoms\n6E62.1 … with manic symptoms\n6E62.2 … with mixed symptoms\n6E62.3 … with unspecified symptoms\nAnxiety and fear-related disorders\n6B00 Generalized anxiety disorder\nSpecify presence of panic attacks without co-occurring panic disorder diagnosis\n6B00/MB23.H Generalized anxiety disorder with panic attacks\n6B01 Panic disorder\n6B02 Agoraphobia\nSpecify presence of panic attacks without co-occurring panic disorder diagnosis\n6B02/MB23.H Agoraphobia with panic attacks\n6B03 Specific phobia\nSpecify presence of panic attacks without co-occurring panic disorder diagnosis\n6B03/MB23.H Specific phobia with panic attacks\n6B04 Social anxiety disorder",
  "metadata": {
    "source": "WHO ICD-11",
    "url": "https://icd.who.int/",
    "condition": "General",
    "risk_band": "low",
    "topics": [
      "screening_cues"
    ],
    "is_clinical": true,
    "is_advice": false
  },
  "index_text": "General — Screening Cues 6C4E.700 … with depressive symptoms\n6C4E.701 … with manic symptoms\n6C4E.702 … with mixed depressive and manic symptoms\n6C4E.70Z … unspecified\n6C4F.70 Mood disorder induced by multiple specified psychoactive\nsubstances\nSpecify clinical presentation:\n6C4F.700 … with depressive symptoms\n6C4F.701 … with manic symptoms\n6C4F.702 … with mixed depressive and manic symptoms\n6C4F.70Z … unspecified\n6C4G.70 Mood disorder induced by unknown or unspecified psychoactive\nsubstances\nSpecify clinical presentation:\n6C4G.700 … with depressive symptoms\n6C4G.701 … with manic symptoms\nList of categories 51\n6C4G.702 … with mixed depressive and manic symptoms\n6C4G.70Z … unspecified\nFrom secondary mental or behavioural syndromes associated with\ndisorders and diseases classified elsewhere:\n6E62 Secondary mood syndrome\nSpecify clinical presentation:\n6E62.0 … with depressive symptoms\n6E62.1 … with manic symptoms\n6E62.2 … with mixed symptoms\n6E62.3 … with unspecified symptoms\nAnxiety and fear-related disorders\n6B00 Generalized anxiety disorder\nSpecify presence of panic attacks without co-occurring panic disorder diagnosis\n6B00/MB23.H Generalized anxiety disorder with panic attacks\n6B01 Panic disorder\n6B02 Agoraphobia\nSpecify presence of panic attacks without co-occurring panic disorder diagnosis\n6B02/MB23.H Agoraphobia with panic attacks\n6B03 Specific phobia\nSpecify presence of panic attacks without co-occurring panic disorder diagnosis\n6B03/MB23.H Specific phobia with panic attacks\n6B04 Social anxiety disorder 6c4e.700 … with depressive symptoms\n6c4e.701 … with manic symptoms\n6c4e.702 … with mixed depressive and manic symptoms\n6c4e.70z … unspecified\n6c4f.70 mood disorder induced by multiple specified psychoactive\nsubstances\nsp..."
}